Metadata-Version: 1.0
Name: python-750g-recipes
Version: 0.2.4
Summary: Easy-to-use Python API for the 750g.com cokking website.
Home-page: https://github.com/remaudcorentin-dev/python-750g-recipes
Author: Corentin Remaud
Author-email: remaudcorentin.dev@gmail.com
License: MIT
Platform: UNKNOWN
